argflow/__init__.py
argflow/exceptions.py
argflow/parser.py
argflow-2.0.0.dist-info/licenses/LICENSE
argflow-2.0.0.dist-info/METADATA
argflow-2.0.0.dist-info/WHEEL
argflow-2.0.0.dist-info/top_level.txt
argflow-2.0.0.dist-info/RECORD
