Metadata-Version: 2.4
Name: argflow
Version: 2.0.0
Summary: The easier and "faster" alternative to argparse.
Home-page: https://github.com/alesisce/argflow
Author: alesisce
License: MIT
Classifier: Programming Language :: Python :: 3
Classifier: License :: OSI Approved :: MIT License
Classifier: Operating System :: OS Independent
Requires-Python: >=3.12
License-File: LICENSE
Dynamic: author
Dynamic: classifier
Dynamic: description
Dynamic: description-content-type
Dynamic: home-page
Dynamic: license
Dynamic: license-file
Dynamic: requires-python
Dynamic: summary
